setup.py
noseapp_alchemy/__init__.py
noseapp_alchemy/base.py
noseapp_alchemy/config.py
noseapp_alchemy/constants.py
noseapp_alchemy/exc.py
noseapp_alchemy/mysql_ex.py
noseapp_alchemy/orm.py
noseapp_alchemy/registry.py
noseapp_alchemy/session.py
noseapp_alchemy.egg-info/PKG-INFO
noseapp_alchemy.egg-info/SOURCES.txt
noseapp_alchemy.egg-info/dependency_links.txt
noseapp_alchemy.egg-info/not-zip-safe
noseapp_alchemy.egg-info/requires.txt
noseapp_alchemy.egg-info/top_level.txt