Metadata-Version: 1.0
Name: noseapp-alchemy
Version: 1.0.0
Summary: SqlAlchemy extension for noseapp lib
Home-page: https://github.com/trifonovmixail/noseapp_alchemy
Author: Mikhail Trifonov
Author-email: mikhail.trifonov@corp.mail.ru
License: UNKNOWN
Platform: any
